LICENSE
impl_pattern/__init__.py
impl_pattern/main.py
impl_pattern-0.1.1.dist-info/LICENSE
impl_pattern-0.1.1.dist-info/WHEEL
impl_pattern-0.1.1.dist-info/METADATA
impl_pattern-0.1.1.dist-info/RECORD
