Metadata-Version: 2.1
Name: impl-pattern
Version: 0.1.1
Summary: 
Home-page: https://github.com/roman-right/impl_pattern
License: Apache-2.0
Keywords: impl,pattern,sync,async,python
Author: Roman
Author-email: roman-right@protonmail.com
Requires-Python: >=3.7
Classifier: License :: OSI Approved :: Apache Software License
Classifier: Programming Language :: Python :: 3
Classifier: Programming Language :: Python :: 3.7
Classifier: Programming Language :: Python :: 3.8
Classifier: Programming Language :: Python :: 3.9
Requires-Dist: asyncio (>=3.4,<4.0)
Project-URL: Repository, https://github.com/roman-right/impl_pattern
